[
    {
        "id":1,
        "img":"https://pic.banggo.com/sources/images/goods/MB/722751/722751_00.jpg?x-oss-process=image/resize,m_fill,w_300,h_410",
        "discout":4.8,
        "name":"男装冬季休闲运动字母印花针织连帽卫衣",
        "price": 180,
        "original":250,
        "smallImg":"https://pic.banggo.com/sources/seller/goods/image/5200545/B14826/B14826_13-5200545-celucasn_01.jpg?x-oss-process=image/resize,m_fill,w_90"
    },
    {
        "id":2,
        "img":"https://pic.banggo.com/sources/images/goods/MB/722751/722751_00.jpg?x-oss-process=image/resize,m_fill,w_300,h_410",
        "discout":4.8,
        "name":"男装冬季休闲运动字母印花针织连帽卫衣",
        "price": 180,
        "original":250,
        "smallImg":"https://pic.banggo.com/sources/seller/goods/image/5200545/B14825/B14825_13-5200545-celucasn_01.jpg?x-oss-process=image/resize,m_fill,w_90"
    },
    {
        "id":3,
        "img":"https://pic.banggo.com/sources/images/goods/MB/722684/722684_00.jpg?x-oss-process=image/resize,m_fill,w_300,h_410",
        "discout":4.8,
        "name":"男装冬季休闲运动字母印花针织连帽卫衣",
        "price": 180,
        "original":250,
        "smallImg":"https://pic.banggo.com/sources/seller/goods/image/5200545/B14826/B14826_13-5200545-celucasn_01.jpg?x-oss-process=image/resize,m_fill,w_90"
    },
    {
        "id":4,
        "img":"https://pic.banggo.com/sources/images/goods/MB/722751/722751_00.jpg?x-oss-process=image/resize,m_fill,w_300,h_410",
        "discout":4.8,
        "name":"男装冬季休闲运动字母印花针织连帽卫衣",
        "price": 180,
        "original":250,
        "smallImg":"https://pic.banggo.com/sources/seller/goods/image/5200545/B14825/B14825_13-5200545-celucasn_01.jpg?x-oss-process=image/resize,m_fill,w_90"
    },
    {
        "id":5,
        "img":"https://pic.banggo.com/sources/images/goods/MB/722751/722751_00.jpg?x-oss-process=image/resize,m_fill,w_300,h_410",
        "discout":4.8,
        "name":"男装冬季休闲运动字母印花针织连帽卫衣",
        "price": 180,
        "original":250,
        "smallImg":"https://pic.banggo.com/sources/seller/goods/image/5200545/B14826/B14826_13-5200545-celucasn_01.jpg?x-oss-process=image/resize,m_fill,w_90"
    },
    {
        "id":6,
        "img":"https://pic.banggo.com/sources/images/goods/MB/722751/722751_00.jpg?x-oss-process=image/resize,m_fill,w_300,h_410",
        "discout":4.8,
        "name":"男装冬季休闲运动字母印花针织连帽卫衣",
        "price": 180,
        "original":250,
        "smallImg":"https://pic.banggo.com/sources/seller/goods/image/5200545/B14825/B14825_13-5200545-celucasn_01.jpg?x-oss-process=image/resize,m_fill,w_90"
    },
    {
        "id":7,
        "img":"https://pic.banggo.com/sources/images/goods/MB/722751/722751_00.jpg?x-oss-process=image/resize,m_fill,w_300,h_410",
        "discout":4.8,
        "name":"男装冬季休闲运动字母印花针织连帽卫衣",
        "price": 180,
        "original":250,
        "smallImg":"https://pic.banggo.com/sources/seller/goods/image/5200545/B14826/B14826_13-5200545-celucasn_01.jpg?x-oss-process=image/resize,m_fill,w_90"
    },
    {
        "id":8,
        "img":"https://pic.banggo.com/sources/images/goods/MB/722751/722751_00.jpg?x-oss-process=image/resize,m_fill,w_300,h_410",
        "discout":4.8,
        "name":"男装冬季休闲运动字母印花针织连帽卫衣",
        "price": 180,
        "original":250,
        "smallImg":"https://pic.banggo.com/sources/seller/goods/image/5200545/B14825/B14825_13-5200545-celucasn_01.jpg?x-oss-process=image/resize,m_fill,w_90"
    },
    {
        "id":9,
        "img":"https://pic.banggo.com/sources/images/goods/MB/722751/722751_00.jpg?x-oss-process=image/resize,m_fill,w_300,h_410",
        "discout":4.8,
        "name":"男装冬季休闲运动字母印花针织连帽卫衣",
        "price": 180,
        "original":250,
        "smallImg":"https://pic.banggo.com/sources/seller/goods/image/5200545/B14826/B14826_13-5200545-celucasn_01.jpg?x-oss-process=image/resize,m_fill,w_90"
    },
    {
        "id":10,
        "img":"https://pic.banggo.com/sources/images/goods/MB/722751/722751_00.jpg?x-oss-process=image/resize,m_fill,w_300,h_410",
        "discout":4.8,
        "name":"男装冬季休闲运动字母印花针织连帽卫衣",
        "price": 180,
        "original":250,
        "smallImg":"https://pic.banggo.com/sources/seller/goods/image/5200545/B14825/B14825_13-5200545-celucasn_01.jpg?x-oss-process=image/resize,m_fill,w_90"
    },
    {
        "id":11,
        "img":"https://pic.banggo.com/sources/images/goods/MB/722751/722751_00.jpg?x-oss-process=image/resize,m_fill,w_300,h_410",
        "discout":4.8,
        "name":"男装冬季休闲运动字母印花针织连帽卫衣",
        "price": 180,
        "original":250,
        "smallImg":"https://pic.banggo.com/sources/seller/goods/image/5200545/B14826/B14826_13-5200545-celucasn_01.jpg?x-oss-process=image/resize,m_fill,w_90"
    },
    {
        "id":12,
        "img":"https://pic.banggo.com/sources/images/goods/MB/722751/722751_00.jpg?x-oss-process=image/resize,m_fill,w_300,h_410",
        "discout":4.8,
        "name":"男装冬季休闲运动字母印花针织连帽卫衣",
        "price": 180,
        "original":250,
        "smallImg":"https://pic.banggo.com/sources/seller/goods/image/5200545/B14825/B14825_13-5200545-celucasn_01.jpg?x-oss-process=image/resize,m_fill,w_90"
    },
    {
        "id":13,
        "img":"https://pic.banggo.com/sources/images/goods/MB/722751/722751_00.jpg?x-oss-process=image/resize,m_fill,w_300,h_410",
        "discout":4.8,
        "name":"男装冬季休闲运动字母印花针织连帽卫衣",
        "price": 180,
        "original":250,
        "smallImg":"https://pic.banggo.com/sources/seller/goods/image/5200545/B14826/B14826_13-5200545-celucasn_01.jpg?x-oss-process=image/resize,m_fill,w_90"
    },
    {
        "id":14,
        "img":"https://pic.banggo.com/sources/images/goods/MB/722751/722751_00.jpg?x-oss-process=image/resize,m_fill,w_300,h_410",
        "discout":4.8,
        "name":"男装冬季休闲运动字母印花针织连帽卫衣",
        "price": 180,
        "original":250,
        "smallImg":"https://pic.banggo.com/sources/seller/goods/image/5200545/B14825/B14825_13-5200545-celucasn_01.jpg?x-oss-process=image/resize,m_fill,w_90"
    },
    {
        "id":15,
        "img":"https://pic.banggo.com/sources/images/goods/MB/722751/722751_00.jpg?x-oss-process=image/resize,m_fill,w_300,h_410",
        "discout":4.8,
        "name":"男装冬季休闲运动字母印花针织连帽卫衣",
        "price": 180,
        "original":250,
        "smallImg":"https://pic.banggo.com/sources/seller/goods/image/5200545/B14826/B14826_13-5200545-celucasn_01.jpg?x-oss-process=image/resize,m_fill,w_90"
    },
    {
        "id":16,
        "img":"https://pic.banggo.com/sources/images/goods/MB/722751/722751_00.jpg?x-oss-process=image/resize,m_fill,w_300,h_410",
        "discout":4.8,
        "name":"男装冬季休闲运动字母印花针织连帽卫衣",
        "price": 180,
        "original":250,
        "smallImg":"https://pic.banggo.com/sources/seller/goods/image/5200545/B14825/B14825_13-5200545-celucasn_01.jpg?x-oss-process=image/resize,m_fill,w_90"
    },
    {
        "id":17,
        "img":"https://pic.banggo.com/sources/images/goods/MB/722751/722751_00.jpg?x-oss-process=image/resize,m_fill,w_300,h_410",
        "discout":4.8,
        "name":"男装冬季休闲运动字母印花针织连帽卫衣",
        "price": 180,
        "original":250,
        "smallImg":"https://pic.banggo.com/sources/seller/goods/image/5200545/B14826/B14826_13-5200545-celucasn_01.jpg?x-oss-process=image/resize,m_fill,w_90"
    },
    {
        "id":18,
        "img":"https://pic.banggo.com/sources/images/goods/MB/722751/722751_00.jpg?x-oss-process=image/resize,m_fill,w_300,h_410",
        "discout":4.8,
        "name":"男装冬季休闲运动字母印花针织连帽卫衣",
        "price": 180,
        "original":250,
        "smallImg":"https://pic.banggo.com/sources/seller/goods/image/5200545/B14825/B14825_13-5200545-celucasn_01.jpg?x-oss-process=image/resize,m_fill,w_90"
    },
    {
        "id":19,
        "img":"https://pic.banggo.com/sources/images/goods/MB/722751/722751_00.jpg?x-oss-process=image/resize,m_fill,w_300,h_410",
        "discout":4.8,
        "name":"男装冬季休闲运动字母印花针织连帽卫衣",
        "price": 180,
        "original":250,
        "smallImg":"https://pic.banggo.com/sources/seller/goods/image/5200545/B14826/B14826_13-5200545-celucasn_01.jpg?x-oss-process=image/resize,m_fill,w_90"
    },
    {
        "id":20,
        "img":"https://pic.banggo.com/sources/images/goods/MB/722751/722751_00.jpg?x-oss-process=image/resize,m_fill,w_300,h_410",
        "discout":4.8,
        "name":"男装冬季休闲运动字母印花针织连帽卫衣",
        "price": 180,
        "original":250,
        "smallImg":"https://pic.banggo.com/sources/seller/goods/image/5200545/B14825/B14825_13-5200545-celucasn_01.jpg?x-oss-process=image/resize,m_fill,w_90"
    },
    {
        "id":1,
        "img":"https://pic.banggo.com/sources/images/goods/MB/722751/722751_00.jpg?x-oss-process=image/resize,m_fill,w_300,h_410",
        "discout":4.8,
        "name":"男装冬季休闲运动字母印花针织连帽卫衣",
        "price": 180,
        "original":250,
        "smallImg":"https://pic.banggo.com/sources/seller/goods/image/5200545/B14826/B14826_13-5200545-celucasn_01.jpg?x-oss-process=image/resize,m_fill,w_90"
    },
    {
        "id":1,
        "img":"https://pic.banggo.com/sources/images/goods/MB/722751/722751_00.jpg?x-oss-process=image/resize,m_fill,w_300,h_410",
        "discout":4.8,
        "name":"男装冬季休闲运动字母印花针织连帽卫衣",
        "price": 180,
        "original":250,
        "smallImg":"https://pic.banggo.com/sources/seller/goods/image/5200545/B14825/B14825_13-5200545-celucasn_01.jpg?x-oss-process=image/resize,m_fill,w_90"
    },
    {
        "id":1,
        "img":"https://pic.banggo.com/sources/images/goods/MB/722751/722751_00.jpg?x-oss-process=image/resize,m_fill,w_300,h_410",
        "discout":4.8,
        "name":"男装冬季休闲运动字母印花针织连帽卫衣",
        "price": 180,
        "original":250,
        "smallImg":"https://pic.banggo.com/sources/seller/goods/image/5200545/B14826/B14826_13-5200545-celucasn_01.jpg?x-oss-process=image/resize,m_fill,w_90"
    },
    {
        "id":1,
        "img":"https://pic.banggo.com/sources/images/goods/MB/722751/722751_00.jpg?x-oss-process=image/resize,m_fill,w_300,h_410",
        "discout":4.8,
        "name":"男装冬季休闲运动字母印花针织连帽卫衣",
        "price": 180,
        "original":250,
        "smallImg":"https://pic.banggo.com/sources/seller/goods/image/5200545/B14825/B14825_13-5200545-celucasn_01.jpg?x-oss-process=image/resize,m_fill,w_90"
    },
    {
        "id":1,
        "img":"https://pic.banggo.com/sources/images/goods/MB/722751/722751_00.jpg?x-oss-process=image/resize,m_fill,w_300,h_410",
        "discout":4.8,
        "name":"男装冬季休闲运动字母印花针织连帽卫衣",
        "price": 180,
        "original":250,
        "smallImg":"https://pic.banggo.com/sources/seller/goods/image/5200545/B14826/B14826_13-5200545-celucasn_01.jpg?x-oss-process=image/resize,m_fill,w_90"
    },
    {
        "id":1,
        "img":"https://pic.banggo.com/sources/images/goods/MB/722751/722751_00.jpg?x-oss-process=image/resize,m_fill,w_300,h_410",
        "discout":4.8,
        "name":"男装冬季休闲运动字母印花针织连帽卫衣",
        "price": 180,
        "original":250,
        "smallImg":"https://pic.banggo.com/sources/seller/goods/image/5200545/B14825/B14825_13-5200545-celucasn_01.jpg?x-oss-process=image/resize,m_fill,w_90"
    },
    {
        "id":1,
        "img":"https://pic.banggo.com/sources/images/goods/MB/722751/722751_00.jpg?x-oss-process=image/resize,m_fill,w_300,h_410",
        "discout":4.8,
        "name":"男装冬季休闲运动字母印花针织连帽卫衣",
        "price": 180,
        "original":250,
        "smallImg":"https://pic.banggo.com/sources/seller/goods/image/5200545/B14826/B14826_13-5200545-celucasn_01.jpg?x-oss-process=image/resize,m_fill,w_90"
    },
    {
        "id":1,
        "img":"https://pic.banggo.com/sources/images/goods/MB/722751/722751_00.jpg?x-oss-process=image/resize,m_fill,w_300,h_410",
        "discout":4.8,
        "name":"男装冬季休闲运动字母印花针织连帽卫衣",
        "price": 180,
        "original":250,
        "smallImg":"https://pic.banggo.com/sources/seller/goods/image/5200545/B14825/B14825_13-5200545-celucasn_01.jpg?x-oss-process=image/resize,m_fill,w_90"
    },
    {
        "id":1,
        "img":"https://pic.banggo.com/sources/images/goods/MB/722751/722751_00.jpg?x-oss-process=image/resize,m_fill,w_300,h_410",
        "discout":4.8,
        "name":"男装冬季休闲运动字母印花针织连帽卫衣",
        "price": 180,
        "original":250,
        "smallImg":"https://pic.banggo.com/sources/seller/goods/image/5200545/B14826/B14826_13-5200545-celucasn_01.jpg?x-oss-process=image/resize,m_fill,w_90"
    },
    {
        "id":1,
        "img":"https://pic.banggo.com/sources/images/goods/MB/722751/722751_00.jpg?x-oss-process=image/resize,m_fill,w_300,h_410",
        "discout":4.8,
        "name":"男装冬季休闲运动字母印花针织连帽卫衣",
        "price": 180,
        "original":250,
        "smallImg":"https://pic.banggo.com/sources/seller/goods/image/5200545/B14825/B14825_13-5200545-celucasn_01.jpg?x-oss-process=image/resize,m_fill,w_90"
    },
    {
        "id":1,
        "img":"https://pic.banggo.com/sources/images/goods/MB/722751/722751_00.jpg?x-oss-process=image/resize,m_fill,w_300,h_410",
        "discout":4.8,
        "name":"男装冬季休闲运动字母印花针织连帽卫衣",
        "price": 180,
        "original":250,
        "smallImg":"https://pic.banggo.com/sources/seller/goods/image/5200545/B14826/B14826_13-5200545-celucasn_01.jpg?x-oss-process=image/resize,m_fill,w_90"
    },
    {
        "id":1,
        "img":"https://pic.banggo.com/sources/images/goods/MB/722751/722751_00.jpg?x-oss-process=image/resize,m_fill,w_300,h_410",
        "discout":4.8,
        "name":"男装冬季休闲运动字母印花针织连帽卫衣",
        "price": 180,
        "original":250,
        "smallImg":"https://pic.banggo.com/sources/seller/goods/image/5200545/B14825/B14825_13-5200545-celucasn_01.jpg?x-oss-process=image/resize,m_fill,w_90"
    },
    {
        "id":1,
        "img":"https://pic.banggo.com/sources/images/goods/MB/722751/722751_00.jpg?x-oss-process=image/resize,m_fill,w_300,h_410",
        "discout":4.8,
        "name":"男装冬季休闲运动字母印花针织连帽卫衣",
        "price": 180,
        "original":250,
        "smallImg":"https://pic.banggo.com/sources/seller/goods/image/5200545/B14826/B14826_13-5200545-celucasn_01.jpg?x-oss-process=image/resize,m_fill,w_90"
    },
    {
        "id":1,
        "img":"https://pic.banggo.com/sources/images/goods/MB/722751/722751_00.jpg?x-oss-process=image/resize,m_fill,w_300,h_410",
        "discout":4.8,
        "name":"男装冬季休闲运动字母印花针织连帽卫衣",
        "price": 180,
        "original":250,
        "smallImg":"https://pic.banggo.com/sources/seller/goods/image/5200545/B14825/B14825_13-5200545-celucasn_01.jpg?x-oss-process=image/resize,m_fill,w_90"
    },
    {
        "id":1,
        "img":"https://pic.banggo.com/sources/images/goods/MB/722751/722751_00.jpg?x-oss-process=image/resize,m_fill,w_300,h_410",
        "discout":4.8,
        "name":"男装冬季休闲运动字母印花针织连帽卫衣",
        "price": 180,
        "original":250,
        "smallImg":"https://pic.banggo.com/sources/seller/goods/image/5200545/B14826/B14826_13-5200545-celucasn_01.jpg?x-oss-process=image/resize,m_fill,w_90"
    },
    {
        "id":1,
        "img":"https://pic.banggo.com/sources/images/goods/MB/722751/722751_00.jpg?x-oss-process=image/resize,m_fill,w_300,h_410",
        "discout":4.8,
        "name":"男装冬季休闲运动字母印花针织连帽卫衣",
        "price": 180,
        "original":250,
        "smallImg":"https://pic.banggo.com/sources/seller/goods/image/5200545/B14825/B14825_13-5200545-celucasn_01.jpg?x-oss-process=image/resize,m_fill,w_90"
    },
    {
        "id":1,
        "img":"https://pic.banggo.com/sources/images/goods/MB/722751/722751_00.jpg?x-oss-process=image/resize,m_fill,w_300,h_410",
        "discout":4.8,
        "name":"男装冬季休闲运动字母印花针织连帽卫衣",
        "price": 180,
        "original":250,
        "smallImg":"https://pic.banggo.com/sources/seller/goods/image/5200545/B14826/B14826_13-5200545-celucasn_01.jpg?x-oss-process=image/resize,m_fill,w_90"
    },
    {
        "id":1,
        "img":"https://pic.banggo.com/sources/images/goods/MB/722751/722751_00.jpg?x-oss-process=image/resize,m_fill,w_300,h_410",
        "discout":4.8,
        "name":"男装冬季休闲运动字母印花针织连帽卫衣",
        "price": 180,
        "original":250,
        "smallImg":"https://pic.banggo.com/sources/seller/goods/image/5200545/B14825/B14825_13-5200545-celucasn_01.jpg?x-oss-process=image/resize,m_fill,w_90"
    },
    {
        "id":1,
        "img":"https://pic.banggo.com/sources/images/goods/MB/722751/722751_00.jpg?x-oss-process=image/resize,m_fill,w_300,h_410",
        "discout":4.8,
        "name":"男装冬季休闲运动字母印花针织连帽卫衣",
        "price": 180,
        "original":250,
        "smallImg":"https://pic.banggo.com/sources/seller/goods/image/5200545/B14826/B14826_13-5200545-celucasn_01.jpg?x-oss-process=image/resize,m_fill,w_90"
    },
    {
        "id":1,
        "img":"https://pic.banggo.com/sources/images/goods/MB/722751/722751_00.jpg?x-oss-process=image/resize,m_fill,w_300,h_410",
        "discout":4.8,
        "name":"男装冬季休闲运动字母印花针织连帽卫衣",
        "price": 180,
        "original":250,
        "smallImg":"https://pic.banggo.com/sources/seller/goods/image/5200545/B14825/B14825_13-5200545-celucasn_01.jpg?x-oss-process=image/resize,m_fill,w_90"
    },
    {
        "id":1,
        "img":"https://pic.banggo.com/sources/images/goods/MB/722751/722751_00.jpg?x-oss-process=image/resize,m_fill,w_300,h_410",
        "discout":4.8,
        "name":"男装冬季休闲运动字母印花针织连帽卫衣",
        "price": 180,
        "original":250,
        "smallImg":"https://pic.banggo.com/sources/seller/goods/image/5200545/B14826/B14826_13-5200545-celucasn_01.jpg?x-oss-process=image/resize,m_fill,w_90"
    },
    {
        "id":1,
        "img":"https://pic.banggo.com/sources/images/goods/MB/722751/722751_00.jpg?x-oss-process=image/resize,m_fill,w_300,h_410",
        "discout":4.8,
        "name":"男装冬季休闲运动字母印花针织连帽卫衣",
        "price": 180,
        "original":250,
        "smallImg":"https://pic.banggo.com/sources/seller/goods/image/5200545/B14825/B14825_13-5200545-celucasn_01.jpg?x-oss-process=image/resize,m_fill,w_90"
    },
    {
        "id":1,
        "img":"https://pic.banggo.com/sources/images/goods/MB/722751/722751_00.jpg?x-oss-process=image/resize,m_fill,w_300,h_410",
        "discout":4.8,
        "name":"男装冬季休闲运动字母印花针织连帽卫衣",
        "price": 180,
        "original":250,
        "smallImg":"https://pic.banggo.com/sources/seller/goods/image/5200545/B14825/B14825_13-5200545-celucasn_01.jpg?x-oss-process=image/resize,m_fill,w_90"
    },
    {
        "id":1,
        "img":"https://pic.banggo.com/sources/images/goods/MB/722751/722751_00.jpg?x-oss-process=image/resize,m_fill,w_300,h_410",
        "discout":4.8,
        "name":"男装冬季休闲运动字母印花针织连帽卫衣",
        "price": 180,
        "original":250,
        "smallImg":"https://pic.banggo.com/sources/seller/goods/image/5200545/B14825/B14825_13-5200545-celucasn_01.jpg?x-oss-process=image/resize,m_fill,w_90"
    },
    {
        "id":1,
        "img":"https://pic.banggo.com/sources/images/goods/MB/722751/722751_00.jpg?x-oss-process=image/resize,m_fill,w_300,h_410",
        "discout":4.8,
        "name":"男装冬季休闲运动字母印花针织连帽卫衣",
        "price": 180,
        "original":250,
        "smallImg":"https://pic.banggo.com/sources/seller/goods/image/5200545/B14825/B14825_13-5200545-celucasn_01.jpg?x-oss-process=image/resize,m_fill,w_90"
    },
    {
        "id":1,
        "img":"https://pic.banggo.com/sources/images/goods/MB/722751/722751_00.jpg?x-oss-process=image/resize,m_fill,w_300,h_410",
        "discout":4.8,
        "name":"男装冬季休闲运动字母印花针织连帽卫衣",
        "price": 180,
        "original":250,
        "smallImg":"https://pic.banggo.com/sources/seller/goods/image/5200545/B14825/B14825_13-5200545-celucasn_01.jpg?x-oss-process=image/resize,m_fill,w_90"
    },
    {
        "id":1,
        "img":"https://pic.banggo.com/sources/images/goods/MB/722751/722751_00.jpg?x-oss-process=image/resize,m_fill,w_300,h_410",
        "discout":4.8,
        "name":"男装冬季休闲运动字母印花针织连帽卫衣",
        "price": 180,
        "original":250,
        "smallImg":"https://pic.banggo.com/sources/seller/goods/image/5200545/B14825/B14825_13-5200545-celucasn_01.jpg?x-oss-process=image/resize,m_fill,w_90"
    },
    {
        "id":1,
        "img":"https://pic.banggo.com/sources/images/goods/MB/722751/722751_00.jpg?x-oss-process=image/resize,m_fill,w_300,h_410",
        "discout":4.8,
        "name":"男装冬季休闲运动字母印花针织连帽卫衣",
        "price": 180,
        "original":250,
        "smallImg":"https://pic.banggo.com/sources/seller/goods/image/5200545/B14825/B14825_13-5200545-celucasn_01.jpg?x-oss-process=image/resize,m_fill,w_90"
    },
    {
        "id":1,
        "img":"https://pic.banggo.com/sources/images/goods/MB/722751/722751_00.jpg?x-oss-process=image/resize,m_fill,w_300,h_410",
        "discout":4.8,
        "name":"男装冬季休闲运动字母印花针织连帽卫衣",
        "price": 180,
        "original":250,
        "smallImg":"https://pic.banggo.com/sources/seller/goods/image/5200545/B14825/B14825_13-5200545-celucasn_01.jpg?x-oss-process=image/resize,m_fill,w_90"
    },
    {
        "id":1,
        "img":"https://pic.banggo.com/sources/images/goods/MB/722751/722751_00.jpg?x-oss-process=image/resize,m_fill,w_300,h_410",
        "discout":4.8,
        "name":"男装冬季休闲运动字母印花针织连帽卫衣",
        "price": 180,
        "original":250,
        "smallImg":"https://pic.banggo.com/sources/seller/goods/image/5200545/B14825/B14825_13-5200545-celucasn_01.jpg?x-oss-process=image/resize,m_fill,w_90"
    }
]